log/__init__.py
pypasswizard-0.3.3.dist-info/licenses/LICENSE
src/__init__.py
src/cli.py
src/core.py
src/utility.py
test/__init__.py
test/test_cli.py
test/test_core.py
test/test_utility.py
pypasswizard-0.3.3.dist-info/METADATA
pypasswizard-0.3.3.dist-info/WHEEL
pypasswizard-0.3.3.dist-info/top_level.txt
pypasswizard-0.3.3.dist-info/RECORD
