Metadata-Version: 2.4
Name: pypasswizard
Version: 0.3.3
Summary: A CLI application for managing passwords securely.
Home-page: https://github.com/0Mr-Panda0/PyPassWizard
Author: 0Mr-Panda0
Author-email: karan.behera366@gmail.com
Requires-Python: >=3.6
License-File: LICENSE
Requires-Dist: click>=8.1.8
Requires-Dist: fastparquet>=2024.11.0
Requires-Dist: funkybob>=2023.12.0
Requires-Dist: mypy>=1.15.0
Requires-Dist: openpyxl>=3.1.5
Requires-Dist: pandas>=2.2.3
Requires-Dist: pandera>=0.23.1
Requires-Dist: pyarrow>=20.0.0
Requires-Dist: pytest>=8.3.5
Requires-Dist: pytest-cov>=6.1.1
Requires-Dist: python-dotenv>=1.1.0
Requires-Dist: ruff>=0.11.7
Requires-Dist: setuptools>=80.0.0
Requires-Dist: tabulate>=0.9.0
Requires-Dist: toml>=0.10.2
Requires-Dist: twine>=6.1.0
Dynamic: author
Dynamic: author-email
Dynamic: home-page
Dynamic: license-file
Dynamic: requires-python
